[
    {
        "lat": "39.88002",
        "lon": "-75.32306",
        "trainno": "1203",
        "service": "LOCAL",
        "dest": "Newark",
        "nextstop": "Crum Lynne",
        "late": 0,
        "SOURCE": "Suburban Station",
        "TRACK": "",
        "TRACK_CHANGE": ""
    },
    {
        "lat": "39.79994",
        "lon": "-75.45059",
        "trainno": "1295",
        "service": "EXP TO RIDLEY PARK-CHESTER",
        "dest": "Newark",
        "nextstop": "Wilmington",
        "late": 4,
        "SOURCE": "Suburban Station",
        "TRACK": "",
        "TRACK_CHANGE": ""
    },
    {
        "lat": "40.07404",
        "lon": "-75.28487",
        "trainno": "207",
        "service": "LOCAL",
        "dest": "Newark",
        "nextstop": "Miquon",
        "late": 3,
        "SOURCE": "Norristown",
        "TRACK": "",
        "TRACK_CHANGE": ""
    },
    {
        "lat": "39.90430",
        "lon": "-75.27096",
        "trainno": "216",
        "service": "LOCAL",
        "dest": "Norristown",
        "nextstop": "Curtis Park",
        "late": 0,
        "SOURCE": "Marcus Hook",
        "TRACK": "",
        "TRACK_CHANGE": ""
    },
    {
        "lat": "39.73740",
        "lon": "-75.55360",
        "trainno": "220",
        "service": "LOCAL",
        "dest": "Norristown",
        "nextstop": "Claymont",
        "late": 0,
        "SOURCE": "Wilmington",
        "TRACK": "",
        "TRACK_CHANGE": ""
    },
    {
        "lat": "40.01272",
        "lon": "-75.16187",
        "trainno": "309",
        "service": "LOCAL",
        "dest": "Elwyn",
        "nextstop": "Temple U",
        "late": 2,
        "SOURCE": "West Trenton",
        "TRACK": "1",
        "TRACK_CHANGE": ""
    },
    {
        "lat": "40.14037",
        "lon": "-74.98259",
        "trainno": "313",
        "service": "LOCAL",
        "dest": "University City",
        "nextstop": "Somerton",
        "late": 0,
        "SOURCE": "West Trenton",
        "TRACK": "",
        "TRACK_CHANGE": ""
    },
    {
        "lat": "39.94452",
        "lon": "-75.23909",
        "trainno": "326",
        "service": "LOCAL",
        "dest": "West Trenton",
        "nextstop": "49th St",
        "late": 3,
        "SOURCE": "Elwyn",
        "TRACK": "",
        "TRACK_CHANGE": ""
    },
    {
        "lat": "40.23531",
        "lon": "-74.83087",
        "trainno": "3505",
        "service": "LTD TO BRYN MAWR & PAOLI",
        "dest": "Paoli",
        "nextstop": "Woodbourne",
        "late": 0,
        "SOURCE": "West Trenton",
        "TRACK": "",
        "TRACK_CHANGE": ""
    },
    {
        "lat": "39.95614",
        "lon": "-75.17938",
        "trainno": "404",
        "service": "LOCAL",
        "dest": "Warminster",
        "nextstop": "Suburban Station",
        "late": 4,
        "SOURCE": "Airport",
        "TRACK": "5",
        "TRACK_CHANGE": ""
    },
    {
        "lat": "39.94651",
        "lon": "-75.19983",
        "trainno": "407",
        "service": "LOCAL",
        "dest": "Airport",
        "nextstop": "Eastwick Station",
        "late": 0,
        "SOURCE": "Warminster",
        "TRACK": "",
        "TRACK_CHANGE": ""
    },
    {
        "lat": "40.05972",
        "lon": "-75.12936",
        "trainno": "409",
        "service": "LOCAL",
        "dest": "Airport",
        "nextstop": "Fern Rock TC",
        "late": 4,
        "SOURCE": "Warminster",
        "TRACK": "",
        "TRACK_CHANGE": ""
    },
    {
        "lat": "39.98060",
        "lon": "-75.14987",
        "trainno": "501",
        "service": "LOCAL",
        "dest": "Paoli",
        "nextstop": "Jefferson Station",
        "late": 5,
        "SOURCE": "Link Belt",
        "TRACK": "",
        "TRACK_CHANGE": ""
    },
    {
        "lat": "40.18449",
        "lon": "-75.25664",
        "trainno": "503",
        "service": "LOCAL",
        "dest": "Thorndale",
        "nextstop": "Penllyn",
        "late": 5,
        "SOURCE": "Doylestown",
        "TRACK": "",
        "TRACK_CHANGE": ""
    },
    {
        "lat": "39.95614",
        "lon": "-75.17938",
        "trainno": "514",
        "service": "LOCAL",
        "dest": "Doylestown",
        "nextstop": "Suburban Station",
        "late": 2,
        "SOURCE": "Thorndale",
        "TRACK": "1",
        "TRACK_CHANGE": ""
    },
    {
        "lat": "40.02158",
        "lon": "-75.31578",
        "trainno": "516",
        "service": "Limited",
        "dest": "Lansdale",
        "nextstop": "Haverford",
        "late": 0,
        "SOURCE": "Malvern",
        "TRACK": "",
        "TRACK_CHANGE": ""
    },
    {
        "lat": "40.04288",
        "lon": "-75.48467",
        "trainno": "5712",
        "service": "LOCAL",
        "dest": "Chestnut H East",
        "nextstop": "Daylesford",
        "late": 1,
        "SOURCE": "Thorndale",
        "TRACK": "",
        "TRACK_CHANGE": ""
    },
    {
        "lat": "40.00386",
        "lon": "-75.16617",
        "trainno": "6212",
        "service": "LOCAL",
        "dest": "Norristown",
        "nextstop": "East Falls",
        "late": 6,
        "SOURCE": "30th St",
        "TRACK": "",
        "TRACK_CHANGE": ""
    },
    {
        "lat": "40.19441",
        "lon": "-74.88312",
        "trainno": "6322",
        "service": "LOCAL",
        "dest": "West Trenton",
        "nextstop": "Yardley",
        "late": 0,
        "SOURCE": "30th St",
        "TRACK": "",
        "TRACK_CHANGE": ""
    },
    {
        "lat": "40.11867",
        "lon": "-75.18549",
        "trainno": "6512",
        "service": "LOCAL",
        "dest": "Lansdale",
        "nextstop": "Ft Washington",
        "late": 1,
        "SOURCE": "30th St",
        "TRACK": "",
        "TRACK_CHANGE": ""
    },
    {
        "lat": "40.03613",
        "lon": "-75.16215",
        "trainno": "705",
        "service": "LOCAL",
        "dest": "Trenton",
        "nextstop": "Wayne Jct",
        "late": 0,
        "SOURCE": "Wayne",
        "TRACK": "",
        "TRACK_CHANGE": ""
    },
    {
        "lat": "40.05458",
        "lon": "-74.98443",
        "trainno": "7218",
        "service": "LOCAL",
        "dest": "Temple U",
        "nextstop": "Holmesburg Jct",
        "late": 0,
        "SOURCE": "Trenton",
        "TRACK": "",
        "TRACK_CHANGE": ""
    },
    {
        "lat": "40.26120",
        "lon": "-74.81410",
        "trainno": "805",
        "service": "LOCAL",
        "dest": "Chestnut H West",
        "nextstop": "Queen Lane",
        "late": 3,
        "SOURCE": "Fox Chase",
        "TRACK": "",
        "TRACK_CHANGE": ""
    },
    {
        "lat": "40.06326",
        "lon": "-75.08735",
        "trainno": "807",
        "service": "LOCAL",
        "dest": "Chestnut H West",
        "nextstop": "Cheltenham",
        "late": 0,
        "SOURCE": "Fox Chase",
        "TRACK": "",
        "TRACK_CHANGE": ""
    },
    {
        "lat": "40.04174",
        "lon": "-75.19044",
        "trainno": "812",
        "service": "LOCAL",
        "dest": "Fox Chase",
        "nextstop": "Tulpehocken",
        "late": 0,
        "SOURCE": "Chestnut H West",
        "TRACK": "",
        "TRACK_CHANGE": ""
    },
    {
        "lat": "40.01417",
        "lon": "-75.30072",
        "trainno": "9597",
        "service": "EXP O'BRK TO ARDMORE",
        "dest": "Thorndale",
        "nextstop": "Bryn Mawr",
        "late": 2,
        "SOURCE": "Temple U",
        "TRACK": "",
        "TRACK_CHANGE": ""
    },
    {
        "lat": "40.13963",
        "lon": "-74.81779",
        "trainno": "9701",
        "service": "LOCAL",
        "dest": "Trenton",
        "nextstop": "Trenton",
        "late": 3,
        "SOURCE": "Temple U",
        "TRACK": "",
        "TRACK_CHANGE": ""
    },
    {
        "lat": "40.00223",
        "lon": "-75.10386",
        "trainno": "9703",
        "service": "LOCAL",
        "dest": "Trenton",
        "nextstop": "Bridesburg",
        "late": 0,
        "SOURCE": "Temple U",
        "TRACK": "",
        "TRACK_CHANGE": ""
    }
]